src/__init__.py
src/main.py
mike_brady-0.5.0.dist-info/LICENSE
mike_brady-0.5.0.dist-info/METADATA
mike_brady-0.5.0.dist-info/WHEEL
mike_brady-0.5.0.dist-info/entry_points.txt
mike_brady-0.5.0.dist-info/top_level.txt
mike_brady-0.5.0.dist-info/RECORD
