Metadata-Version: 2.1
Name: mike-brady
Version: 0.5.0
Summary: Create a repo from a repo blueprint
Home-page: https://github.com/troylar/mike-brady
Author: Troy Larson
Author-email: troylar@gmail.com
License: MIT
Platform: UNKNOWN
Classifier: License :: OSI Approved :: MIT License
Classifier: Programming Language :: Python
Classifier: Programming Language :: Python :: 3
Classifier: Programming Language :: Python :: 3.6
Classifier: Programming Language :: Python :: Implementation :: CPython
Classifier: Programming Language :: Python :: Implementation :: PyPy
Requires-Python: >=3.6.0
Requires-Dist: click
Requires-Dist: gitpython
Requires-Dist: jinja2
